semantext/__init__.py
semantext/star_schema.py
semantext/helper_models/__init__.py
semantext/helper_models/general_types.py
semantext/models/__init__.py
semantext/models/chart_properties.py
semantext/models/table.py
semantext/utils/__init__.py
semantext/utils/sql_helper.py
semantext/utils/validator.py
semantext-0.3.8.dist-info/METADATA
semantext-0.3.8.dist-info/WHEEL
semantext-0.3.8.dist-info/licenses/LICENSE
semantext-0.3.8.dist-info/RECORD
