Metadata-Version: 2.4
Name: semantext
Version: 0.3.8
Summary: OSS Semantic Layer built for easy llm integration
Author-email: Alon Nahmias <alon.alon.nahmias@gmail.com>, Shoham Yamin <shoham39@gmail.com>
License:                                  Apache License
License-File: LICENSE
Requires-Python: >=3.12
Requires-Dist: pydantic>=2.11.7
Requires-Dist: sqlglot>=26.30.0
